pydantic_serializable/__init__.py
pydantic_serializable/serializable.py
pydantic_serializable-0.1.3.dist-info/LICENSE
pydantic_serializable-0.1.3.dist-info/METADATA
pydantic_serializable-0.1.3.dist-info/WHEEL
pydantic_serializable-0.1.3.dist-info/RECORD
